firelit/__init__.py
firelit/admin.py
firelit/frontend.py
firelit/utils.py
firelit-0.1.5.dist-info/LICENSE
firelit-0.1.5.dist-info/METADATA
firelit-0.1.5.dist-info/WHEEL
firelit-0.1.5.dist-info/RECORD
