Metadata-Version: 2.1
Name: firelit
Version: 0.1.5
Summary: 🔥👑 FireLit: Streamlit App with Firebase Authentication
License: MIT
Author: GitMarco27
Author-email: marco.sanguineti.info@gmail.com
Requires-Python: >=3.10,<4.0
Classifier: License :: OSI Approved :: MIT License
Classifier: Programming Language :: Python :: 3
Classifier: Programming Language :: Python :: 3.10
Classifier: Programming Language :: Python :: 3.11
Requires-Dist: Pyrebase4 (>=4.7.1,<5.0.0)
Requires-Dist: pyyaml (>=6.0.1,<7.0.0)
Requires-Dist: streamlit (>=1.27.1,<2.0.0)
